wordcanvas/__init__.py
wordcanvas/custom_aug.py
wordcanvas/font_utils.py
wordcanvas/mrz_generator.py
wordcanvas/text_image_renderer.py
wordcanvas/word_canvas.py
wordcanvas/barcode/__init__.py
wordcanvas/barcode/code128_table.json
wordcanvas/barcode/code128table.py
wordcanvas/barcode/code39_table.json
wordcanvas/barcode/code39table.py
wordcanvas/barcode/gen_barcode.py
wordcanvas/fonts/NotoSansTC-Regular.otf
wordcanvas/fonts/OcrB-Regular.ttf
wordcanvas_docsaid-2.1.0.dist-info/LICENSE
wordcanvas_docsaid-2.1.0.dist-info/METADATA
wordcanvas_docsaid-2.1.0.dist-info/WHEEL
wordcanvas_docsaid-2.1.0.dist-info/top_level.txt
wordcanvas_docsaid-2.1.0.dist-info/RECORD
