Metadata-Version: 2.1
Name: wordcanvas-docsaid
Version: 2.1.0
Summary: Generating text with custom fonts and styles.
Home-page: https://github.com/DocsaidLab/WordCanvas.git
License: Apache License 2.0
Classifier: Development Status :: 5 - Production/Stable
Classifier: License :: OSI Approved :: Apache Software License
Classifier: Intended Audience :: Developers
Classifier: Intended Audience :: Science/Research
Classifier: Operating System :: OS Independent
Classifier: Programming Language :: Python :: 3.10
Classifier: Programming Language :: Python :: 3.11
Classifier: Programming Language :: Python :: 3.12
Classifier: Topic :: Software Development :: Libraries
Classifier: Topic :: Software Development :: Libraries :: Python Modules
License-File: LICENSE
Requires-Dist: capybara-docsaid>=0.6.0
Requires-Dist: fonttools
Requires-Dist: pillow
Requires-Dist: pandas
Requires-Dist: regex
Requires-Dist: numpy
Requires-Dist: lxml
Requires-Dist: prettytable
Requires-Dist: albumentations
